LICENSE
jake/__init__.py
jake/app.py
jake/command/__init__.py
jake/command/config.py
jake/command/iq.py
jake/command/oss.py
jake/command/parser_selector.py
jake/command/sbom.py
jake/py.typed
jake-3.0.14.dist-info/LICENSE
jake-3.0.14.dist-info/METADATA
jake-3.0.14.dist-info/WHEEL
jake-3.0.14.dist-info/entry_points.txt
jake-3.0.14.dist-info/RECORD
