Metadata-Version: 2.1
Name: jake
Version: 3.0.14
Summary: An OSS Index integration to check for vulnerabilities in your Python environments
Home-page: https://github.com/sonatype-nexus-community/jake
License: Apache-2.0
Keywords: BOM,SBOM,SCA,OWASP
Author: Sonatype Community
Author-email: community-group@sonatype.com
Maintainer: Sonatype Community
Maintainer-email: community-group@sonatype.com
Requires-Python: >=3.8,<4.0
Classifier: Development Status :: 5 - Production/Stable
Classifier: Intended Audience :: Developers
Classifier: Intended Audience :: Information Technology
Classifier: Intended Audience :: Legal Industry
Classifier: Intended Audience :: System Administrators
Classifier: License :: OSI Approved :: Apache Software License
Classifier: Programming Language :: Python :: 3
Classifier: Programming Language :: Python :: 3.8
Classifier: Programming Language :: Python :: 3.9
Classifier: Programming Language :: Python :: 3.10
Classifier: Programming Language :: Python :: 3.11
Classifier: Programming Language :: Python :: 3.7
Classifier: Topic :: Security
Classifier: Topic :: Software Development
Classifier: Topic :: System :: Software Distribution
Classifier: Typing :: Typed
Requires-Dist: cyclonedx-bom (>=3.0.0,<4.0.0)
Requires-Dist: importlib-metadata (>=3.7) ; python_version < "3.8"
Requires-Dist: ossindex-lib (>=1.0.0,<2.0.0)
Requires-Dist: polling2 (>=0.5.0,<0.6.0)
Requires-Dist: pyfiglet (>=0.7.6,<1.0.0)
Requires-Dist: requests (>=2.32.3,<3.0.0)
Requires-Dist: rich (>=10.10.0)
Project-URL: Bug Tracker, https://github.com/sonatype-nexus-community/jake/issues
Project-URL: Repository, https://github.com/sonatype-nexus-community/jake
